pt2d/__init__.py
pt2d/circle_edge_kernel.py
pt2d/compute_cost_image.py
pt2d/compute_disk_size.py
pt2d/downscale.py
pt2d/find_path.py
pt2d/load_image.py
pt2d/preprocess_image.py
pt2d/gui/__init__.py
pt2d/gui/advancedSettingsWidget.py
pt2d/gui/circleEditorGraphicsView.py
pt2d/gui/circleEditorWidget.py
pt2d/gui/draggableCircleItem.py
pt2d/gui/imageGraphicsView.py
pt2d/gui/labeledPointItem.py
pt2d/gui/mainWindow.py
pt2d/gui/panZoomGraphicsView.py
pt2d-0.1.4.dist-info/LICENSE
pt2d-0.1.4.dist-info/METADATA
pt2d-0.1.4.dist-info/WHEEL
pt2d-0.1.4.dist-info/entry_points.txt
pt2d-0.1.4.dist-info/top_level.txt
pt2d-0.1.4.dist-info/RECORD
