Metadata-Version: 2.2
Name: pt2d
Version: 0.1.4
Summary: Interactive path tracing in 2D medical images
Home-page: https://lab.compute.dtu.dk/QIM/tools/pt2d
Author: Aske T. Rove, Christian L. Bjerregaard, Mikkel W. Breinstrup
Author-email: s224362@dtu.dk, s224389@dtu.dk, s224361@dtu.dk
Classifier: License :: OSI Approved :: MIT License
Classifier: Programming Language :: Python :: 3
Classifier: Development Status :: 3 - Alpha
Classifier: Intended Audience :: Education
Classifier: Intended Audience :: Science/Research
Classifier: Natural Language :: English
Classifier: Operating System :: OS Independent
Classifier: Topic :: Scientific/Engineering :: Image Processing
Classifier: Topic :: Scientific/Engineering :: Visualization
Classifier: Topic :: Software Development :: User Interfaces
Requires-Python: >=3.10
License-File: LICENSE
Requires-Dist: numpy<=1.26.4
Requires-Dist: opencv_python>=4.9.0.80
Requires-Dist: PyQt5>=5.15.11
Requires-Dist: PyQt5_sip>=12.11.1
Requires-Dist: scipy>=1.15.1
Requires-Dist: scikit-image>=0.23.2
Dynamic: author
Dynamic: author-email
Dynamic: classifier
Dynamic: description
Dynamic: description-content-type
Dynamic: home-page
Dynamic: requires-dist
Dynamic: requires-python
Dynamic: summary
